pyhuntress/__init__.py
pyhuntress/config.py
pyhuntress/exceptions.py
pyhuntress/interfaces.py
pyhuntress/py.typed
pyhuntress/types.py
pyhuntress/clients/__init__.py
pyhuntress/clients/huntress_client.py
pyhuntress/clients/managedsat_client.py
pyhuntress/clients/siem_client.py
pyhuntress/endpoints/__init__.py
pyhuntress/endpoints/base/__init__.py
pyhuntress/endpoints/base/huntress_endpoint.py
pyhuntress/endpoints/managedsat/AccountsEndpoint.py
pyhuntress/endpoints/managedsat/AccountsIdAssignmentsEndpoint.py
pyhuntress/endpoints/managedsat/AccountsIdDepartmentsEndpoint.py
pyhuntress/endpoints/managedsat/AccountsIdEndpoint.py
pyhuntress/endpoints/managedsat/AccountsIdGroupsEndpoint.py
pyhuntress/endpoints/managedsat/AccountsIdLearnersEndpoint.py
pyhuntress/endpoints/managedsat/AccountsIdPhishingCampaignsEndpoint.py
pyhuntress/endpoints/managedsat/AccountsIdPhishingScenariosEndpoint.py
pyhuntress/endpoints/managedsat/AccountsIdUsersEndpoint.py
pyhuntress/endpoints/managedsat/AssignmentsEndpoint.py
pyhuntress/endpoints/managedsat/AssignmentsIdCompletionCertificateEndpoint.py
pyhuntress/endpoints/managedsat/AssignmentsIdEndpoint.py
pyhuntress/endpoints/managedsat/AssignmentsIdEnrollmentConditionsEndpoint.py
pyhuntress/endpoints/managedsat/AssignmentsIdEnrollmentExtrasEndpoint.py
pyhuntress/endpoints/managedsat/AssignmentsIdLearnerActivityEndpoint.py
pyhuntress/endpoints/managedsat/AssignmentsIdLearnersEndpoint.py
pyhuntress/endpoints/managedsat/DepartmentsEndpoint.py
pyhuntress/endpoints/managedsat/DepartmentsIdEndpoint.py
pyhuntress/endpoints/managedsat/EpisodesEndpoint.py
pyhuntress/endpoints/managedsat/EpisodesIdEndpoint.py
pyhuntress/endpoints/managedsat/GroupsEndpoint.py
pyhuntress/endpoints/managedsat/GroupsIdEndpoint.py
pyhuntress/endpoints/managedsat/LearnersEndpoint.py
pyhuntress/endpoints/managedsat/LearnersIdEndpoint.py
pyhuntress/endpoints/managedsat/PhishingAttemptsActionsEndpoint.py
pyhuntress/endpoints/managedsat/PhishingAttemptsActionsReportEndpoint.py
pyhuntress-0.2.16.dist-info/METADATA
pyhuntress-0.2.16.dist-info/WHEEL
pyhuntress-0.2.16.dist-info/licenses/LICENSE
pyhuntress-0.2.16.dist-info/RECORD
