Metadata-Version: 2.4
Name: pyhuntress
Version: 0.2.16
Summary: A full-featured Python client for the Huntress APIs
Project-URL: Homepage, https://github.com/brygphilomena/pyhuntress
Project-URL: Issues, https://github.com/brygphilomena/pyhuntress/issues
Author-email: Peter Annabel <peter.annabel@gmail.com>
License-Expression: GPL-3.0-only
License-File: LICENSE
Keywords: API,Annotated,Client,Huntress,MSP,Manages SAT,Python,SIEM,Typed
Classifier: Intended Audience :: Developers
Classifier: License :: OSI Approved :: GNU General Public License v3 or later (GPLv3+)
Classifier: Programming Language :: Python :: 3.10
Classifier: Programming Language :: Python :: 3.11
Classifier: Topic :: Software Development :: Libraries :: Python Modules
Requires-Python: >=3.9
Requires-Dist: pydantic
Requires-Dist: requests
Requires-Dist: typing-extensions
